NetworkUtilities/__init__.py
NetworkUtilities/__main__.py
NetworkUtilities/version.py
NetworkUtilities/core/__init__.py
NetworkUtilities/core/ipv4_network.py
NetworkUtilities/core/ipv4_network_compound.py
NetworkUtilities/utils/__init__.py
NetworkUtilities/utils/errors.py
NetworkUtilities/utils/ip_class.py
NetworkUtilities/utils/utils.py
nettools/__init__.py
nettools/__main__.py
nettools/version.py
nettools/core/__init__.py
nettools/core/ipv4_network.py
nettools/core/ipv4_network_compound.py
nettools/utils/__init__.py
nettools/utils/errors.py
nettools/utils/ip_class.py
nettools/utils/utils.py
nettools-2.0.1.data/scripts/runtests
nettools-2.0.1.dist-info/LICENSE
nettools-2.0.1.dist-info/METADATA
nettools-2.0.1.dist-info/WHEEL
nettools-2.0.1.dist-info/top_level.txt
nettools-2.0.1.dist-info/RECORD
