Metadata-Version: 2.1
Name: nettools
Version: 2.0.1
Summary: A tool allowing to create, calculate and manipulate networks and subnetworks easily
Home-page: https://github.com/BioTheWolff/NetworkUtilities
Author: Fabien Z.
Author-email: contact.biowolf@gmx.fr
Maintainer: Fabien Z.
Maintainer-email: contact.biowolf@gmx.fr
License: MIT
Project-URL: Source Code, https://github.com/BioTheWolff/NetworkUtilities
Project-URL: Bug Tracker, https://github.com/BioTheWolff/NetworkUtilities/issues
Platform: UNKNOWN
Classifier: Development Status :: 5 - Production/Stable
Classifier: Intended Audience :: Developers
Classifier: Intended Audience :: System Administrators
Classifier: Topic :: Utilities
Classifier: Programming Language :: Python :: 3
Classifier: License :: OSI Approved :: MIT License
Classifier: Operating System :: OS Independent
Requires-Python: >=3.6
